micron/__init__.py
micron-1.0.post1.dist-info/LICENSE
micron-1.0.post1.dist-info/METADATA
micron-1.0.post1.dist-info/WHEEL
micron-1.0.post1.dist-info/entry_points.txt
micron-1.0.post1.dist-info/top_level.txt
micron-1.0.post1.dist-info/RECORD
