Metadata-Version: 2.1
Name: micron
Version: 1.0.post1
Summary: minimal cron alternative for containers
Home-page: https://github.com/nlm/micron
Author: Nicolas Limage
Author-email: github@xephon.org
License: MIT
Keywords: crontab container
Platform: UNKNOWN
Classifier: Development Status :: 4 - Beta
Classifier: Environment :: Console
Classifier: Intended Audience :: System Administrators
Classifier: License :: OSI Approved :: MIT License
Classifier: Operating System :: Unix
Classifier: Programming Language :: Python
Classifier: Topic :: Utilities
Requires-Python: >=3.6
Requires-Dist: crontab
